{"acc17330-eec1-11eb-98f1-afb9f64778ee":{"room_id":"acc17330-eec1-11eb-98f1-afb9f64778ee","instance_id":"instance_0","pin":"acc17332-eec1-11eb-98f1-afb9f64778ee","secret":"acc17331-eec1-11eb-98f1-afb9f64778ee","participants":[],"room":"acc17330-eec1-11eb-98f1-afb9f64778ee","description":"Cool vp9 room (0)","pin_required":true,"max_publishers":6,"bitrate":512000,"fir_freq":0,"require_pvtid":false,"require_e2ee":false,"notify_joining":false,"audiocodec":"opus","videocodec":"vp8","record":false,"lock_record":false,"num_participants":0,"audiolevel_ext":true,"audiolevel_event":false,"videoorient_ext":true,"playoutdelay_ext":true,"transport_wide_cc_ext":true},"acc320e0-eec1-11eb-98f1-afb9f64778ee":{"room_id":"acc320e0-eec1-11eb-98f1-afb9f64778ee","instance_id":"instance_1","pin":"acc320e2-eec1-11eb-98f1-afb9f64778ee","secret":"acc320e1-eec1-11eb-98f1-afb9f64778ee","participants":[],"room":"acc320e0-eec1-11eb-98f1-afb9f64778ee","description":"Cool vp8 room (1)","pin_required":true,"max_publishers":6,"bitrate":512000,"fir_freq":0,"require_pvtid":false,"require_e2ee":false,"notify_joining":false,"audiocodec":"opus","videocodec":"vp9","record":false,"lock_record":false,"num_participants":0,"audiolevel_ext":true,"audiolevel_event":false,"videoorient_ext":true,"playoutdelay_ext":true,"transport_wide_cc_ext":true},"acc45960-eec1-11eb-98f1-afb9f64778ee":{"room_id":"acc45960-eec1-11eb-98f1-afb9f64778ee","instance_id":"instance_0","pin":"acc45962-eec1-11eb-98f1-afb9f64778ee","secret":"acc45961-eec1-11eb-98f1-afb9f64778ee","participants":[],"room":"acc45960-eec1-11eb-98f1-afb9f64778ee","description":"Cool vp9 room (2)","pin_required":true,"max_publishers":6,"bitrate":512000,"fir_freq":0,"require_pvtid":false,"require_e2ee":false,"notify_joining":false,"audiocodec":"opus","videocodec":"vp9","record":false,"lock_record":false,"num_participants":0,"audiolevel_ext":true,"audiolevel_event":false,"videoorient_ext":true,"playoutdelay_ext":true,"transport_wide_cc_ext":true},"acc56ad0-eec1-11eb-98f1-afb9f64778ee":{"room_id":"acc56ad0-eec1-11eb-98f1-afb9f64778ee","instance_id":"instance_1","pin":"acc56ad2-eec1-11eb-98f1-afb9f64778ee","secret":"acc56ad1-eec1-11eb-98f1-afb9f64778ee","participants":[],"room":"acc56ad0-eec1-11eb-98f1-afb9f64778ee","description":"Cool vp8 room (3)","pin_required":true,"max_publishers":6,"bitrate":512000,"fir_freq":0,"require_pvtid":false,"require_e2ee":false,"notify_joining":false,"audiocodec":"opus","videocodec":"vp9","record":false,"lock_record":false,"num_participants":0,"audiolevel_ext":true,"audiolevel_event":false,"videoorient_ext":true,"playoutdelay_ext":true,"transport_wide_cc_ext":true},"acc6a350-eec1-11eb-98f1-afb9f64778ee":{"room_id":"acc6a350-eec1-11eb-98f1-afb9f64778ee","instance_id":"instance_0","pin":"acc6a352-eec1-11eb-98f1-afb9f64778ee","secret":"acc6a351-eec1-11eb-98f1-afb9f64778ee","participants":[],"room":"acc6a350-eec1-11eb-98f1-afb9f64778ee","description":"Cool vp9 room (4)","pin_required":true,"max_publishers":6,"bitrate":512000,"fir_freq":0,"require_pvtid":false,"require_e2ee":false,"notify_joining":false,"audiocodec":"opus","videocodec":"vp9","record":false,"lock_record":false,"num_participants":0,"audiolevel_ext":true,"audiolevel_event":false,"videoorient_ext":true,"playoutdelay_ext":true,"transport_wide_cc_ext":true}}